README.md
setup.py
tap_s3_csv/__init__.py
tap_s3_csv/config.py
tap_s3_csv/conversion.py
tap_s3_csv/discover.py
tap_s3_csv/s3.py
tap_s3_csv/sync.py
tap_s3_csv_koszti.egg-info/PKG-INFO
tap_s3_csv_koszti.egg-info/SOURCES.txt
tap_s3_csv_koszti.egg-info/dependency_links.txt
tap_s3_csv_koszti.egg-info/entry_points.txt
tap_s3_csv_koszti.egg-info/requires.txt
tap_s3_csv_koszti.egg-info/top_level.txt