Metadata-Version: 2.1
Name: tap-s3-csv-koszti
Version: 1.0.2
Summary: Singer.io tap for extracting CSV files from S3
Home-page: https://singer.io
Author: Stitch
License: UNKNOWN
Platform: UNKNOWN
Classifier: Programming Language :: Python :: 3 :: Only
Provides-Extra: dev
